{
  "date": "2026-04-02",
  "venue": "桐生",
  "jcd": "01",
  "day": 2,
  "total_days": null,
  "day_label": "2日目",
  "event_title": "DKカップ 桐生歴代ファイナリスト頂上決戦",
  "grade_label": "一般",
  "race": {
    "rno": 12,
    "name": "桐生特選",
    "shinin": "",
    "distance_m": 1800,
    "cutoff": "20:38",
    "boats": [
      {
        "waku": 1,
        "regno": 4335,
        "name": "若林将",
        "age": 42,
        "branch": "東京",
        "weight": 55,
        "grade": "A1",
        "nat_win": 7.24,
        "nat_2": 53.4,
        "loc_win": 7.63,
        "loc_2": 66.67,
        "motor_no": 38,
        "motor_2": 43.18,
        "boat_no": 22,
        "boat_2": 32.05,
        "note": "14 5",
        "avg_st": 0.12,
        "st_count": 738,
        "course_starts": 58,
        "course_win": 72.4,
        "course_2ren": 87.9,
        "course_3ren": 91.4,
        "course_avg_st": 0.11,
        "course_sashi": 0,
        "course_makuri": 0,
        "course_makurisashi": 0,
        "f_count": 0,
        "l_count": 0,
        "meet_perf": [
          [
            {
              "course": 5,
              "st": ".14",
              "rank": 1
            },
            {
              "course": 2,
              "st": ".19",
              "rank": 4
            }
          ],
          [
            null,
            null
          ],
          [
            null,
            null
          ],
          [
            null,
            null
          ],
          [
            null,
            null
          ],
          [
            null,
            null
          ],
          [
            null,
            null
          ]
        ]
      },
      {
        "waku": 2,
        "regno": 3251,
        "name": "平石和男",
        "age": 59,
        "branch": "埼玉",
        "weight": 51,
        "grade": "A2",
        "nat_win": 5.72,
        "nat_2": 39.52,
        "loc_win": 5.18,
        "loc_2": 32.35,
        "motor_no": 40,
        "motor_2": 32.76,
        "boat_no": 51,
        "boat_2": 37.5,
        "note": "4 8",
        "avg_st": 0.193,
        "st_count": 873,
        "course_starts": 49,
        "course_win": 14.3,
        "course_2ren": 46.9,
        "course_3ren": 61.2,
        "course_avg_st": 0.19,
        "course_sashi": 0,
        "course_makuri": 2,
        "course_makurisashi": 0,
        "f_count": 0,
        "l_count": 0,
        "meet_perf": [
          [
            {
              "course": 6,
              "st": ".23",
              "rank": 4
            },
            null
          ],
          [
            null,
            null
          ],
          [
            null,
            null
          ],
          [
            null,
            null
          ],
          [
            null,
            null
          ],
          [
            null,
            null
          ],
          [
            null,
            null
          ]
        ]
      },
      {
        "waku": 3,
        "regno": 4983,
        "name": "前田篤哉",
        "age": 29,
        "branch": "愛知",
        "weight": 52,
        "grade": "A1",
        "nat_win": 7.07,
        "nat_2": 56.52,
        "loc_win": 6.49,
        "loc_2": 48.57,
        "motor_no": 59,
        "motor_2": 38.46,
        "boat_no": 33,
        "boat_2": 33.77,
        "note": "56 6",
        "avg_st": 0.166,
        "st_count": 800,
        "course_starts": 36,
        "course_win": 25.0,
        "course_2ren": 61.1,
        "course_3ren": 80.6,
        "course_avg_st": 0.18,
        "course_sashi": 0,
        "course_makuri": 0,
        "course_makurisashi": 7,
        "f_count": 0,
        "l_count": 0,
        "meet_perf": [
          [
            {
              "course": 5,
              "st": ".21",
              "rank": 5
            },
            {
              "course": 6,
              "st": ".16",
              "rank": 6
            }
          ],
          [
            null,
            null
          ],
          [
            null,
            null
          ],
          [
            null,
            null
          ],
          [
            null,
            null
          ],
          [
            null,
            null
          ],
          [
            null,
            null
          ]
        ]
      },
      {
        "waku": 4,
        "regno": 4281,
        "name": "大澤大夢",
        "age": 42,
        "branch": "埼玉",
        "weight": 54,
        "grade": "B1",
        "nat_win": 4.9,
        "nat_2": 29.58,
        "loc_win": 5.0,
        "loc_2": 22.22,
        "motor_no": 34,
        "motor_2": 36.11,
        "boat_no": 37,
        "boat_2": 36.25,
        "note": "3 4",
        "avg_st": 0.16,
        "st_count": 635,
        "course_starts": 32,
        "course_win": 12.5,
        "course_2ren": 25.0,
        "course_3ren": 46.9,
        "course_avg_st": 0.16,
        "course_sashi": 0,
        "course_makuri": 2,
        "course_makurisashi": 1,
        "f_count": 0,
        "l_count": 0,
        "meet_perf": [
          [
            {
              "course": 5,
              "st": ".23",
              "rank": 3
            },
            null
          ],
          [
            null,
            null
          ],
          [
            null,
            null
          ],
          [
            null,
            null
          ],
          [
            null,
            null
          ],
          [
            null,
            null
          ],
          [
            null,
            null
          ]
        ]
      },
      {
        "waku": 5,
        "regno": 5029,
        "name": "中亮太",
        "age": 28,
        "branch": "福岡",
        "weight": 53,
        "grade": "A2",
        "nat_win": 6.28,
        "nat_2": 46.67,
        "loc_win": 4.72,
        "loc_2": 28.0,
        "motor_no": 56,
        "motor_2": 43.55,
        "boat_no": 58,
        "boat_2": 28.0,
        "note": "13 7",
        "avg_st": 0.13,
        "st_count": 736,
        "course_starts": 38,
        "course_win": 7.9,
        "course_2ren": 18.4,
        "course_3ren": 39.5,
        "course_avg_st": 0.14,
        "course_sashi": 0,
        "course_makuri": 1,
        "course_makurisashi": 2,
        "f_count": 0,
        "l_count": 0,
        "meet_perf": [
          [
            {
              "course": 4,
              "st": ".11",
              "rank": 1
            },
            {
              "course": 6,
              "st": ".13",
              "rank": 3
            }
          ],
          [
            null,
            null
          ],
          [
            null,
            null
          ],
          [
            null,
            null
          ],
          [
            null,
            null
          ],
          [
            null,
            null
          ],
          [
            null,
            null
          ]
        ]
      },
      {
        "waku": 6,
        "regno": 4988,
        "name": "牟田奨太",
        "age": 28,
        "branch": "静岡",
        "weight": 56,
        "grade": "B1",
        "nat_win": 4.45,
        "nat_2": 32.94,
        "loc_win": 4.0,
        "loc_2": 28.0,
        "motor_no": 21,
        "motor_2": 31.58,
        "boat_no": 36,
        "boat_2": 45.21,
        "note": "15 3",
        "avg_st": 0.144,
        "st_count": 610,
        "course_starts": 31,
        "course_win": 3.2,
        "course_2ren": 6.5,
        "course_3ren": 12.9,
        "course_avg_st": 0.16,
        "course_sashi": 0,
        "course_makuri": 0,
        "course_makurisashi": 1,
        "f_count": 0,
        "l_count": 0,
        "meet_perf": [
          [
            {
              "course": 1,
              "st": ".19",
              "rank": 1
            },
            {
              "course": 5,
              "st": ".10",
              "rank": 5
            }
          ],
          [
            null,
            null
          ],
          [
            null,
            null
          ],
          [
            null,
            null
          ],
          [
            null,
            null
          ],
          [
            null,
            null
          ],
          [
            null,
            null
          ]
        ]
      }
    ],
    "tags": []
  },
  "meet_day_no": 2
}