{
  "date": "2026-03-25",
  "venue": "丸亀",
  "jcd": "15",
  "day": 7,
  "total_days": null,
  "day_label": "7日目",
  "event_title": "丸亀市観光協会杯",
  "grade_label": "一般",
  "race": {
    "rno": 11,
    "name": "特別選抜戦",
    "shinin": "",
    "distance_m": 1800,
    "cutoff": "20:01",
    "boats": [
      {
        "waku": 1,
        "regno": 4715,
        "name": "村上遼",
        "age": 33,
        "branch": "長崎",
        "weight": 54,
        "grade": "A1",
        "nat_win": 6.42,
        "nat_2": 42.73,
        "loc_win": 3.58,
        "loc_2": 16.67,
        "motor_no": 37,
        "motor_2": 26.09,
        "boat_no": 27,
        "boat_2": 37.91,
        "note": "2 2351361313 7",
        "avg_st": 0.128,
        "st_count": 662
      },
      {
        "waku": 2,
        "regno": 4497,
        "name": "桑原悠",
        "age": 38,
        "branch": "長崎",
        "weight": 54,
        "grade": "A1",
        "nat_win": 6.33,
        "nat_2": 38.64,
        "loc_win": 7.94,
        "loc_2": 70.59,
        "motor_no": 10,
        "motor_2": 25.71,
        "boat_no": 52,
        "boat_2": 39.22,
        "note": "43164 113144 8",
        "avg_st": 0.138,
        "st_count": 684
      },
      {
        "waku": 3,
        "regno": 4376,
        "name": "藤田靖弘",
        "age": 41,
        "branch": "静岡",
        "weight": 52,
        "grade": "A2",
        "nat_win": 5.63,
        "nat_2": 38.28,
        "loc_win": 4.77,
        "loc_2": 25.64,
        "motor_no": 1,
        "motor_2": 25.64,
        "boat_no": 57,
        "boat_2": 20.83,
        "note": "3 4135352214 7",
        "avg_st": 0.157,
        "st_count": 840
      },
      {
        "waku": 4,
        "regno": 3572,
        "name": "安田政彦",
        "age": 54,
        "branch": "兵庫",
        "weight": 53,
        "grade": "A2",
        "nat_win": 4.87,
        "nat_2": 25.83,
        "loc_win": 5.43,
        "loc_2": 34.04,
        "motor_no": 4,
        "motor_2": 33.04,
        "boat_no": 34,
        "boat_2": 37.84,
        "note": "3 2425335415 6",
        "avg_st": 0.198,
        "st_count": 473
      },
      {
        "waku": 5,
        "regno": 5032,
        "name": "谷口知優",
        "age": 28,
        "branch": "香川",
        "weight": 52,
        "grade": "B1",
        "nat_win": 5.53,
        "nat_2": 30.68,
        "loc_win": 5.07,
        "loc_2": 27.84,
        "motor_no": 64,
        "motor_2": 32.14,
        "boat_no": 48,
        "boat_2": 25.17,
        "note": "1 266 161426 4",
        "avg_st": 0.161,
        "st_count": 564
      },
      {
        "waku": 6,
        "regno": 5249,
        "name": "三木晴斗",
        "age": 23,
        "branch": "徳島",
        "weight": 52,
        "grade": "B1",
        "nat_win": 5.38,
        "nat_2": 33.67,
        "loc_win": 3.06,
        "loc_2": 12.9,
        "motor_no": 45,
        "motor_2": 38.6,
        "boat_no": 49,
        "boat_2": 31.33,
        "note": "5 153 161516 6",
        "avg_st": 0.162,
        "st_count": 559
      }
    ],
    "tags": []
  }
}