{
  "date": "2026-04-01",
  "venue": "桐生",
  "jcd": "01",
  "day": 1,
  "total_days": null,
  "day_label": "初日",
  "event_title": "DKカップ 桐生歴代ファイナリスト頂上決戦",
  "grade_label": "一般",
  "race": {
    "rno": 4,
    "name": "予選",
    "shinin": "",
    "distance_m": 1800,
    "cutoff": "16:43",
    "boats": [
      {
        "waku": 1,
        "regno": 4509,
        "name": "平見真彦",
        "age": 37,
        "branch": "愛知",
        "weight": 54,
        "grade": "B1",
        "nat_win": 5.88,
        "nat_2": 33.68,
        "loc_win": 6.56,
        "loc_2": 50.0,
        "motor_no": 71,
        "motor_2": 32.2,
        "boat_no": 65,
        "boat_2": 20.51,
        "note": "8",
        "avg_st": 0.172,
        "st_count": 806,
        "course_starts": 44,
        "course_win": 45.5,
        "course_2ren": 70.5,
        "course_3ren": 81.8,
        "course_avg_st": 0.17,
        "course_sashi": 0,
        "course_makuri": 0,
        "course_makurisashi": 0,
        "meet_perf": []
      },
      {
        "waku": 2,
        "regno": 4594,
        "name": "谷川祐一",
        "age": 44,
        "branch": "滋賀",
        "weight": 54,
        "grade": "A2",
        "nat_win": 5.17,
        "nat_2": 27.78,
        "loc_win": 5.94,
        "loc_2": 38.89,
        "motor_no": 25,
        "motor_2": 39.22,
        "boat_no": 43,
        "boat_2": 32.05,
        "note": "",
        "avg_st": 0.148,
        "st_count": 715,
        "course_starts": 31,
        "course_win": 25.8,
        "course_2ren": 54.8,
        "course_3ren": 58.1,
        "course_avg_st": 0.17,
        "course_sashi": 4,
        "course_makuri": 1,
        "course_makurisashi": 0,
        "meet_perf": []
      },
      {
        "waku": 3,
        "regno": 3362,
        "name": "間嶋仁志",
        "age": 56,
        "branch": "三重",
        "weight": 56,
        "grade": "B1",
        "nat_win": 5.59,
        "nat_2": 41.98,
        "loc_win": 5.18,
        "loc_2": 36.92,
        "motor_no": 53,
        "motor_2": 42.31,
        "boat_no": 44,
        "boat_2": 47.44,
        "note": "9",
        "avg_st": 0.188,
        "st_count": 730,
        "course_starts": 37,
        "course_win": 10.8,
        "course_2ren": 29.7,
        "course_3ren": 51.4,
        "course_avg_st": 0.18,
        "course_sashi": 1,
        "course_makuri": 2,
        "course_makurisashi": 1,
        "meet_perf": []
      },
      {
        "waku": 4,
        "regno": 3805,
        "name": "高橋英之",
        "age": 51,
        "branch": "東京",
        "weight": 53,
        "grade": "A2",
        "nat_win": 4.76,
        "nat_2": 23.88,
        "loc_win": 5.13,
        "loc_2": 30.43,
        "motor_no": 30,
        "motor_2": 52.08,
        "boat_no": 59,
        "boat_2": 39.74,
        "note": "10",
        "avg_st": 0.133,
        "st_count": 640,
        "course_starts": 26,
        "course_win": 7.7,
        "course_2ren": 38.5,
        "course_3ren": 69.2,
        "course_avg_st": 0.11,
        "course_sashi": 0,
        "course_makuri": 2,
        "course_makurisashi": 0,
        "meet_perf": []
      },
      {
        "waku": 5,
        "regno": 4109,
        "name": "谷津幸宏",
        "age": 45,
        "branch": "埼玉",
        "weight": 56,
        "grade": "A1",
        "nat_win": 5.86,
        "nat_2": 39.83,
        "loc_win": 6.7,
        "loc_2": 47.37,
        "motor_no": 50,
        "motor_2": 35.71,
        "boat_no": 55,
        "boat_2": 31.94,
        "note": "11",
        "avg_st": 0.126,
        "st_count": 803,
        "course_starts": 34,
        "course_win": 20.6,
        "course_2ren": 23.5,
        "course_3ren": 47.1,
        "course_avg_st": 0.12,
        "course_sashi": 1,
        "course_makuri": 3,
        "course_makurisashi": 3,
        "meet_perf": []
      },
      {
        "waku": 6,
        "regno": 4625,
        "name": "渡邊裕貴",
        "age": 40,
        "branch": "静岡",
        "weight": 54,
        "grade": "B1",
        "nat_win": 4.77,
        "nat_2": 30.86,
        "loc_win": 3.6,
        "loc_2": 15.56,
        "motor_no": 65,
        "motor_2": 34.29,
        "boat_no": 28,
        "boat_2": 50.0,
        "note": "",
        "avg_st": 0.156,
        "st_count": 603,
        "course_starts": 29,
        "course_win": 0.0,
        "course_2ren": 0.0,
        "course_3ren": 3.4,
        "course_avg_st": 0.17,
        "course_sashi": 0,
        "course_makuri": 0,
        "course_makurisashi": 0,
        "meet_perf": []
      }
    ],
    "tags": []
  },
  "meet_day_no": 1
}