{
  "date": "2026-03-28",
  "venue": "下関",
  "jcd": "19",
  "day": 3,
  "total_days": null,
  "day_label": "3日目",
  "event_title": "KRY山口放送杯争奪戦",
  "grade_label": "一般",
  "race": {
    "rno": 7,
    "name": "ふく〜る特賞",
    "shinin": "",
    "distance_m": 1800,
    "cutoff": "18:16",
    "boats": [
      {
        "waku": 1,
        "regno": 5003,
        "name": "来田衣織",
        "age": 29,
        "branch": "兵庫",
        "weight": 46,
        "grade": "B1",
        "nat_win": 5.01,
        "nat_2": 36.73,
        "loc_win": 4.0,
        "loc_2": 21.05,
        "motor_no": 59,
        "motor_2": 36.91,
        "boat_no": 52,
        "boat_2": 34.68,
        "note": "3 62",
        "avg_st": 0.183,
        "st_count": 607
      },
      {
        "waku": 2,
        "regno": 4592,
        "name": "小林孝弘",
        "age": 45,
        "branch": "山口",
        "weight": 51,
        "grade": "B1",
        "nat_win": 4.72,
        "nat_2": 25.69,
        "loc_win": 4.11,
        "loc_2": 21.33,
        "motor_no": 33,
        "motor_2": 32.89,
        "boat_no": 14,
        "boat_2": 33.8,
        "note": "4666",
        "avg_st": 0.16,
        "st_count": 656
      },
      {
        "waku": 3,
        "regno": 4560,
        "name": "庄司樹良々",
        "age": 35,
        "branch": "東京",
        "weight": 56,
        "grade": "A2",
        "nat_win": 6.09,
        "nat_2": 41.38,
        "loc_win": 5.17,
        "loc_2": 26.09,
        "motor_no": 55,
        "motor_2": 29.24,
        "boat_no": 30,
        "boat_2": 33.03,
        "note": "5 35 12",
        "avg_st": 0.152,
        "st_count": 599
      },
      {
        "waku": 4,
        "regno": 5138,
        "name": "村本大成",
        "age": 25,
        "branch": "福岡",
        "weight": 53,
        "grade": "B2",
        "nat_win": 3.7,
        "nat_2": 12.5,
        "loc_win": 2.45,
        "loc_2": 5.0,
        "motor_no": 48,
        "motor_2": 31.76,
        "boat_no": 55,
        "boat_2": 35.75,
        "note": "565 3",
        "avg_st": 0.18,
        "st_count": 363
      },
      {
        "waku": 5,
        "regno": 4584,
        "name": "村岡賢人",
        "age": 36,
        "branch": "岡山",
        "weight": 54,
        "grade": "A1",
        "nat_win": 6.79,
        "nat_2": 50.41,
        "loc_win": 6.97,
        "loc_2": 47.06,
        "motor_no": 43,
        "motor_2": 39.29,
        "boat_no": 73,
        "boat_2": 35.14,
        "note": "3211",
        "avg_st": 0.119,
        "st_count": 771
      },
      {
        "waku": 6,
        "regno": 4593,
        "name": "小坂宗司",
        "age": 45,
        "branch": "大阪",
        "weight": 52,
        "grade": "A2",
        "nat_win": 6.28,
        "nat_2": 40.95,
        "loc_win": 5.57,
        "loc_2": 42.86,
        "motor_no": 58,
        "motor_2": 29.85,
        "boat_no": 20,
        "boat_2": 34.84,
        "note": "4 63 11",
        "avg_st": 0.158,
        "st_count": 645
      }
    ],
    "tags": []
  }
}