{
  "date": "2026-03-28",
  "venue": "唐津",
  "jcd": "23",
  "day": 1,
  "total_days": null,
  "day_label": "初日",
  "event_title": "私のイケメン選手権",
  "grade_label": "一般",
  "race": {
    "rno": 7,
    "name": "予選",
    "shinin": "",
    "distance_m": 1800,
    "cutoff": "11:33",
    "boats": [
      {
        "waku": 1,
        "regno": 4651,
        "name": "佐藤大騎",
        "age": 41,
        "branch": "大阪",
        "weight": 53,
        "grade": "B1",
        "nat_win": 4.17,
        "nat_2": 24.68,
        "loc_win": 4.88,
        "loc_2": 23.08,
        "motor_no": 12,
        "motor_2": 36.27,
        "boat_no": 30,
        "boat_2": 22.22,
        "note": "",
        "avg_st": 0.16,
        "st_count": 534
      },
      {
        "waku": 2,
        "regno": 3841,
        "name": "佐々木和伸",
        "age": 49,
        "branch": "徳島",
        "weight": 54,
        "grade": "A2",
        "nat_win": 5.98,
        "nat_2": 41.12,
        "loc_win": 5.47,
        "loc_2": 36.84,
        "motor_no": 23,
        "motor_2": 23.47,
        "boat_no": 41,
        "boat_2": 33.33,
        "note": "11",
        "avg_st": 0.169,
        "st_count": 699
      },
      {
        "waku": 3,
        "regno": 4565,
        "name": "西村豪洋",
        "age": 38,
        "branch": "愛知",
        "weight": 54,
        "grade": "B1",
        "nat_win": 3.88,
        "nat_2": 15.63,
        "loc_win": 4.16,
        "loc_2": 8.0,
        "motor_no": 56,
        "motor_2": 28.26,
        "boat_no": 25,
        "boat_2": 55.56,
        "note": "",
        "avg_st": 0.173,
        "st_count": 559
      },
      {
        "waku": 4,
        "regno": 4471,
        "name": "新田泰章",
        "age": 38,
        "branch": "広島",
        "weight": 53,
        "grade": "A1",
        "nat_win": 7.11,
        "nat_2": 55.56,
        "loc_win": 6.63,
        "loc_2": 54.35,
        "motor_no": 3,
        "motor_2": 24.71,
        "boat_no": 13,
        "boat_2": 44.44,
        "note": "12",
        "avg_st": 0.156,
        "st_count": 775
      },
      {
        "waku": 5,
        "regno": 4330,
        "name": "奈須啓太",
        "age": 42,
        "branch": "福岡",
        "weight": 52,
        "grade": "A2",
        "nat_win": 5.82,
        "nat_2": 40.37,
        "loc_win": 6.43,
        "loc_2": 55.0,
        "motor_no": 25,
        "motor_2": 36.26,
        "boat_no": 40,
        "boat_2": 22.22,
        "note": "",
        "avg_st": 0.123,
        "st_count": 603
      },
      {
        "waku": 6,
        "regno": 4406,
        "name": "幸野史明",
        "age": 40,
        "branch": "福岡",
        "weight": 51,
        "grade": "B1",
        "nat_win": 4.26,
        "nat_2": 26.26,
        "loc_win": 5.29,
        "loc_2": 38.71,
        "motor_no": 33,
        "motor_2": 24.07,
        "boat_no": 46,
        "boat_2": 33.33,
        "note": "1",
        "avg_st": 0.164,
        "st_count": 672
      }
    ],
    "tags": []
  }
}