{
  "date": "2026-03-28",
  "venue": "戸田",
  "jcd": "02",
  "day": 1,
  "total_days": null,
  "day_label": "初日",
  "event_title": "日本トーター・SODAカップ",
  "grade_label": "一般",
  "race": {
    "rno": 8,
    "name": "予選",
    "shinin": "",
    "distance_m": 1800,
    "cutoff": "14:16",
    "boats": [
      {
        "waku": 1,
        "regno": 3619,
        "name": "長谷川充",
        "age": 52,
        "branch": "群馬",
        "weight": 52,
        "grade": "B1",
        "nat_win": 4.9,
        "nat_2": 31.18,
        "loc_win": 4.49,
        "loc_2": 19.15,
        "motor_no": 51,
        "motor_2": 33.83,
        "boat_no": 38,
        "boat_2": 40.6,
        "note": "2",
        "avg_st": 0.191,
        "st_count": 722
      },
      {
        "waku": 2,
        "regno": 3974,
        "name": "深山祐二",
        "age": 49,
        "branch": "佐賀",
        "weight": 52,
        "grade": "B1",
        "nat_win": 4.37,
        "nat_2": 23.53,
        "loc_win": 4.08,
        "loc_2": 7.69,
        "motor_no": 1,
        "motor_2": 26.83,
        "boat_no": 70,
        "boat_2": 38.85,
        "note": "",
        "avg_st": 0.159,
        "st_count": 539
      },
      {
        "waku": 3,
        "regno": 4973,
        "name": "栗原直也",
        "age": 33,
        "branch": "埼玉",
        "weight": 52,
        "grade": "A2",
        "nat_win": 4.99,
        "nat_2": 29.73,
        "loc_win": 5.03,
        "loc_2": 29.35,
        "motor_no": 2,
        "motor_2": 40.91,
        "boat_no": 42,
        "boat_2": 42.96,
        "note": "",
        "avg_st": 0.185,
        "st_count": 641
      },
      {
        "waku": 4,
        "regno": 4158,
        "name": "木場雄二郎",
        "age": 44,
        "branch": "山口",
        "weight": 58,
        "grade": "B1",
        "nat_win": 5.39,
        "nat_2": 36.96,
        "loc_win": 3.43,
        "loc_2": 14.29,
        "motor_no": 7,
        "motor_2": 33.78,
        "boat_no": 59,
        "boat_2": 40.77,
        "note": "3",
        "avg_st": 0.166,
        "st_count": 691
      },
      {
        "waku": 5,
        "regno": 4680,
        "name": "後藤美翼",
        "age": 36,
        "branch": "東京",
        "weight": 46,
        "grade": "B1",
        "nat_win": 5.61,
        "nat_2": 34.69,
        "loc_win": 4.74,
        "loc_2": 29.63,
        "motor_no": 20,
        "motor_2": 29.25,
        "boat_no": 20,
        "boat_2": 32.39,
        "note": "4",
        "avg_st": 0.203,
        "st_count": 630
      },
      {
        "waku": 6,
        "regno": 4294,
        "name": "古賀繁輝",
        "age": 39,
        "branch": "佐賀",
        "weight": 58,
        "grade": "A1",
        "nat_win": 6.79,
        "nat_2": 52.24,
        "loc_win": 6.96,
        "loc_2": 48.15,
        "motor_no": 16,
        "motor_2": 40.0,
        "boat_no": 57,
        "boat_2": 27.94,
        "note": "12",
        "avg_st": 0.148,
        "st_count": 727
      }
    ],
    "tags": []
  }
}